xia_pattern/__init__.py
xia_pattern/pattern.cpython-39-darwin.so
xia_pattern/regularize.cpython-39-darwin.so
xia_pattern/templates/patterns/python/initial/.gitlab-ci.yml
xia_pattern/templates/patterns/python/initial/requirements-dev.txt
xia_pattern/templates/patterns/python/initial/requirements.txt
xia_pattern/templates/patterns/python/templates/__init__.py.tpl
xia_pattern/templates/patterns/python/templates/main.py.tpl
xia_pattern/templates/patterns/python/templates/module.py.tpl
xia_pattern/templates/patterns/python/templates/test_unit.py.tpl
xia_pattern-0.0.8.dist-info/LICENSE.txt
xia_pattern-0.0.8.dist-info/METADATA
xia_pattern-0.0.8.dist-info/WHEEL
xia_pattern-0.0.8.dist-info/top_level.txt
xia_pattern-0.0.8.dist-info/RECORD
